agent_starter_pack/agents/README.md
agent_starter_pack/agents/adk/README.md
agent_starter_pack/agents/adk/.template/templateconfig.yaml
agent_starter_pack/agents/adk/app/__init__.py
agent_starter_pack/agents/adk/app/agent.py
agent_starter_pack/agents/adk/notebooks/adk_app_testing.ipynb
agent_starter_pack/agents/adk/notebooks/evaluating_adk_agent.ipynb
agent_starter_pack/agents/adk/tests/integration/test_agent.py
agent_starter_pack/agents/adk_a2a/README.md
agent_starter_pack/agents/adk_a2a/.template/templateconfig.yaml
agent_starter_pack/agents/adk_a2a/app/__init__.py
agent_starter_pack/agents/adk_a2a/app/agent.py
agent_starter_pack/agents/adk_a2a/notebooks/adk_a2a_app_testing.ipynb
agent_starter_pack/agents/adk_a2a/notebooks/evaluating_adk_agent.ipynb
agent_starter_pack/agents/adk_a2a/tests/integration/test_agent.py
agent_starter_pack/agents/adk_go/.template/templateconfig.yaml
agent_starter_pack/agents/adk_go/agent/agent.go
agent_starter_pack/agents/adk_go/agent/agent_test.go
agent_starter_pack/agents/adk_live/README.md
agent_starter_pack/agents/adk_live/.template/templateconfig.yaml
agent_starter_pack/agents/adk_live/app/__init__.py
agent_starter_pack/agents/adk_live/app/agent.py
agent_starter_pack/agents/adk_live/tests/unit/test_dummy.py
agent_starter_pack/agents/agentic_rag/README.md
agent_starter_pack/agents/agentic_rag/.template/templateconfig.yaml
agent_starter_pack/agents/agentic_rag/app/__init__.py
agent_starter_pack/agents/agentic_rag/app/agent.py
agent_starter_pack/agents/agentic_rag/app/retrievers.py
agent_starter_pack/agents/agentic_rag/app/templates.py
agent_starter_pack/agents/agentic_rag/notebooks/adk_app_testing.ipynb
agent_starter_pack/agents/agentic_rag/notebooks/evaluating_adk_agent.ipynb
agent_starter_pack/agents/agentic_rag/tests/integration/test_agent.py
agent_starter_pack/agents/langgraph/README.md
agent_starter_pack/agents/langgraph/.template/templateconfig.yaml
agent_starter_pack/agents/langgraph/app/__init__.py
agent_starter_pack-0.32.0.dist-info/METADATA
agent_starter_pack-0.32.0.dist-info/WHEEL
agent_starter_pack-0.32.0.dist-info/entry_points.txt
agent_starter_pack-0.32.0.dist-info/licenses/LICENSE
agent_starter_pack-0.32.0.dist-info/RECORD
