Metadata-Version: 2.4
Name: agent-starter-pack
Version: 0.32.0
Summary: CLI to bootstrap production-ready Google Cloud GenAI agent projects from templates.
Author-email: Google LLC <agent-starter-pack@google.com>
License: Apache-2.0
License-File: LICENSE
Requires-Python: >=3.10
Requires-Dist: backoff>=2.2.1
Requires-Dist: click>=8.1.7
Requires-Dist: cookiecutter<3.0.0,>=2.6.0
Requires-Dist: google-cloud-aiplatform>=1.120.0
Requires-Dist: pyyaml>=6.0.1
Requires-Dist: requests>=2.31.0
Requires-Dist: rich>=13.7.0
Requires-Dist: tomli>=1.1.0; python_version < '3.11'
Provides-Extra: jupyter
Requires-Dist: ipykernel>=6.29.5; extra == 'jupyter'
Requires-Dist: jupyter; extra == 'jupyter'
Provides-Extra: lint
Requires-Dist: codespell; extra == 'lint'
Requires-Dist: ruff; extra == 'lint'
Requires-Dist: ty; extra == 'lint'
